polars_xdt-0.17.1.dist-info/METADATA
polars_xdt-0.17.1.dist-info/WHEEL
polars_xdt-0.17.1.dist-info/licenses/LICENSE
polars_xdt/.mypy.ini
polars_xdt/__init__.py
polars_xdt/_internal.abi3.so
polars_xdt/_internal.pyi
polars_xdt/functions.py
polars_xdt/namespace.py
polars_xdt/py.typed
polars_xdt/ranges.py
polars_xdt/typing.py
polars_xdt/utils.py
polars_xdt-0.17.1.dist-info/RECORD
