Metadata-Version: 2.4
Name: polars-xdt
Version: 0.17.1
Classifier: Programming Language :: Rust
Classifier: Programming Language :: Python :: Implementation :: CPython
Classifier: Programming Language :: Python :: Implementation :: PyPy
License-File: LICENSE
Summary: eXtra stuff for Dates and Times in Polars
Author-email: Marco Gorelli <33491632+MarcoGorelli@users.noreply.github.com>
Requires-Python: >=3.9
Project-URL: Repository, https://github.com/MarcoGorelli/polars-xdt
Project-URL: Documentation, https://marcogorelli.github.io/polars-xdt-docs/
Project-URL: Change Log, https://github.com/MarcoGorelli/polars-xdt/releases
Project-URL: Issue Tracker, https://github.com/MarcoGorelli/polars-xdt/issues
